Workbook
Name IN_ANCHOR_CLIENTS: Assumptions!$B$21
Name IN_AVG_CHAT_DURATION: Assumptions!$B$13
Name IN_AVG_VOICE_DURATION: Assumptions!$B$12
Name IN_ELEVEN_BASE_USD_MO: Assumptions!$B$17
Name IN_ELEVEN_USD_MIN: Assumptions!$B$8
Name IN_FIXED_ALLOC_CLIENTS: Assumptions!$B$22
Name IN_FX_EUR_AUD: Assumptions!$B$6
Name IN_FX_USD_AUD: Assumptions!$B$5
Name IN_INBOUND_RATIO: Assumptions!$B$14
Name IN_N8N_HOST_USD_MO: Assumptions!$B$16
Name IN_RETELL_KB_USD_MO: Assumptions!$B$19
Name IN_RETELL_USD_MIN: Assumptions!$B$7
Name IN_SUPABASE_USD_MO: Assumptions!$B$15
Name IN_TARGET_GM: Assumptions!$B$20
Name IN_TWILIO_IN_AUD_MIN: Assumptions!$B$9
Name IN_TWILIO_NUMBER_AUD: Assumptions!$B$11
Name IN_TWILIO_OUT_AUD_MIN: Assumptions!$B$10
Name IN_VERCEL_AUD_MO: Assumptions!$B$18

Sheet Cover
A1: Penny SAAS — Pricing Model
A3: Prepared 18 May 2026 • For founder review • AUD pricing • AU/NZ market
A5: This workbook is the math foundation of the Penny pricing proposal.
A7: How to use this model:
A8: 1. Open the 'Assumptions' tab — edit any yellow input cell to change cost or pricing inputs.
A9: 2. The 'Tier Economics' and 'Scenarios' tabs recalculate automatically.
A10: 3. Use 'Year-1 Projection' to model anchor-client ramp (5 → 10 clients).
A11: 4. 'Setup Fees', 'Fixed Costs', and 'Risk Register' are reference tabs.
A13: Conventions:
A14: • Yellow cells = editable inputs (founder can tweak)
A15: • White cells with borders = calculated outputs
A16: • All currency in AUD unless explicitly noted as USD/EUR
... A27: • Risk Register — 6 cost-risk callouts with mitigations

Sheet Assumptions
A1: Assumptions (editable inputs)
A2: Yellow cells are editable. All other tabs recalculate from these.
A4: Input | B4: Value | C4: Format | D4: Notes
A5: USD → AUD | B5: 1.55 | C5: 0.0000 | D5: FX rate. Used to convert USD-priced services to AUD.
A6: EUR → AUD | B6: 1.65 | C6: 0.0000 | D6: FX rate. Used to convert EUR-priced services (n8n) to AUD.
A7: Retell all-in (USD/min) | B7: 0.2 | C7: $#,##0.0000 | D7: Retell voice: infra + ElevenLabs TTS + GPT-4o LLM. Range $0.07–$0.31 depending on voice.
A8: ElevenLabs ConvAI (USD/min) | B8: 0.08 | C8: $#,##0.0000 | D8: Chat agent per-min. Standard $0.08, Turbo $0.10, Premium $0.12.
A9: Twilio AU inbound local (AUD/min) | B9: 0.01 | C9: $#,##0.0000 | D9: AU local inbound rate.
A10: Twilio AU outbound local (AUD/min) | B10: 0.0252 | C10: $#,##0.0000 | D10: AU outbound local. Mobile outbound is 3x ($0.075).
A11: Twilio AU local number (AUD/mo) | B11: 3 | C11: $#,##0.00 | D11: Monthly rental per dedicated client number.
A12: Avg voice call duration (min) | B12: 5 | C12: 0.0 | D12: Used for per-call COGS calculation.
A13: Avg chat session duration (min) | B13: 5 | C13: 0.0 | D13: ElevenLabs bills session duration even for text chat.
A14: Inbound call ratio (%) | B14: 0.85 | C14: 0% | D14: Most calls inbound. Outbound campaigns priced separately.
A15: Supabase Pro (USD/mo) | B15: 25 | C15: $#,##0.00 | D15: Fixed platform cost. Covers all clients up to 100K MAU.
A16: n8n Hostinger KVM 2 (USD/mo) | B16: 8.99 | C16: $#,##0.00 | D16: Recommended self-host. n8n Cloud Pro is €50 if you stay on cloud.
... A22: Fixed-cost allocation across (clients) | B22: 10 | C22: 0 | D22: Number of clients sharing fixed platform costs. Conservative = use 8.

Sheet COGS Calculator
A1: COGS Calculator (per minute / per session)
A2: Variable cost per unit. Drives tier overage rates and margin math.
A4: Voice call — cost per minute (AUD)
A5: Layer | B5: Source | C5: Rate | D5: Currency factor | E5: AUD/min
A6: Retell AI (infra+TTS+LLM) | B6: Assumptions | C6: =Assumptions!$B$7 -> 0.2 | D6: =Assumptions!$B$5 -> 1.55 | E6: =Assumptions!$B$7*Assumptions!$B$5 -> 0.31
A7: Twilio inbound (weighted) | B7: Assumptions | C7: =Assumptions!$B$9 -> 0.01 | D7: =Assumptions!$B$14 -> 0.85 | E7: =Assumptions!$B$14*Assumptions!$B$9 -> 0.0085
A8: Twilio outbound (weighted) | B8: Assumptions | C8: =Assumptions!$B$10 -> 0.0252 | D8: =1-Assumptions!$B$14 -> 0.15 | E8: =(1-Assumptions!$B$14)*Assumptions!$B$10 -> 0.00378
A9: TOTAL voice AUD/min | E9: =SUM(E6:E8) -> 0.32228
A11: ="Per-call cost ("&Assumptions!$B$12&"min avg)" -> Per-call cost (5min avg) | E11: =$E$9*Assumptions!$B$12 -> 1.6114
A14: Chat session — cost per minute (AUD)
A15: Layer | B15: Source | C15: Rate | D15: Currency factor | E15: AUD/min
A16: ElevenLabs ConvAI | B16: Assumptions | C16: =Assumptions!$B$8 -> 0.08 | D16: =Assumptions!$B$5 -> 1.55 | E16: =Assumptions!$B$8*Assumptions!$B$5 -> 0.124
A17: TOTAL chat AUD/min | E17: =$E$16 -> 0.124
A19: ="Per-session cost ("&Assumptions!$B$13&"min avg)" -> Per-session cost (5min avg) | E19: =$E$16*Assumptions!$B$13 -> 0.62
A22: Overage markup math
A23: Channel | B23: Cost AUD/min | C23: Overage AUD/min | D23: Markup multiple | E23: Markup %
A24: Voice — Starter overage | B24: =$E$9 -> 0.32228 | C24: 1.2 | D24: =C24/B24 -> 3.7234703 | E24: =(C24-B24)/B24 -> 2.7234703
A25: Voice — Growth overage | B25: =$E$9 -> 0.32228 | C25: 1 | D25: =C25/B25 -> 3.1028919 | E25: =(C25-B25)/B25 -> 2.1028919
A26: Voice — Scale overage | B26: =$E$9 -> 0.32228 | C26: 0.85 | D26: =C26/B26 -> 2.6374581 | E26: =(C26-B26)/B26 -> 1.6374581
A27: Chat — Starter overage | B27: =$E$16 -> 0.124 | C27: 0.55 | D27: =C27/B27 -> 4.4354839 | E27: =(C27-B27)/B27 -> 3.4354839
A28: Chat — Growth overage | B28: =$E$16 -> 0.124 | C28: 0.45 | D28: =C28/B28 -> 3.6290323 | E28: =(C28-B28)/B28 -> 2.6290323
A29: Chat — Scale overage | B29: =$E$16 -> 0.124 | C29: 0.4 | D29: =C29/B29 -> 3.2258065 | E29: =(C29-B29)/B29 -> 2.2258065

Sheet Tier Economics
A1: Tier Economics (revenue, COGS, margin at full utilisation)
A2: Assumes 100% of included usage consumed. Real-world utilisation often 60–80%.
A4: Tier | B4: Monthly AUD | C4: Voice min (inc.) | D4: Chat min (inc.) | E4: Voice $/min over | F4: Chat $/min over | G4: Variable COGS (at cap)
A5: Starter | B5: 499 | C5: 200 | D5: 500 | E5: 1.2 | F5: 0.55 | G5: =C5*((Assumptions!$B$7*Assumptions!$B$5) + (Assumptions!$B$14*Assumptions!$B$9) + ((1-Assumptions!$B$14)*Assumptions!$B$10)) + D5*((Assumptions!$B$8*Assumptions!$B$5)) -> 126.456
A6: Growth | B6: 1499 | C6: 800 | D6: 2000 | E6: 1 | F6: 0.45 | G6: =C6*((Assumptions!$B$7*Assumptions!$B$5) + (Assumptions!$B$14*Assumptions!$B$9) + ((1-Assumptions!$B$14)*Assumptions!$B$10)) + D6*((Assumptions!$B$8*Assumptions!$B$5)) -> 505.824
A7: Scale | B7: 3999 | C7: 2500 | D7: 6000 | E7: 0.85 | F7: 0.4 | G7: =C7*((Assumptions!$B$7*Assumptions!$B$5) + (Assumptions!$B$14*Assumptions!$B$9) + ((1-Assumptions!$B$14)*Assumptions!$B$10)) + D7*((Assumptions!$B$8*Assumptions!$B$5)) -> 1549.7
A8: Enterprise | B8: 7500 | C8: 5500 | D8: 13000 | E8: 0.7 | F8: 0.35 | G8: =C8*((Assumptions!$B$7*Assumptions!$B$5) + (Assumptions!$B$14*Assumptions!$B$9) + ((1-Assumptions!$B$14)*Assumptions!$B$10)) + D8*((Assumptions!$B$8*Assumptions!$B$5)) -> 3384.54
A10: Fixed cost allocation per client (shared across all clients)
A11: Component | B11: USD/mo | C11: EUR/mo | D11: FX | E11: AUD/mo | F11: ÷ N clients | G11: AUD/client/mo
A12: Supabase Pro | B12: =Assumptions!$B$15 -> 25 | D12: =Assumptions!$B$5 -> 1.55 | E12: =B12*D12 -> 38.75 | F12: =Assumptions!$B$22 -> 10 | G12: =E12/F12 -> 3.875
A13: n8n Hostinger KVM 2 | B13: =Assumptions!$B$16 -> 8.99 | D13: =Assumptions!$B$5 -> 1.55 | E13: =B13*D13 -> 13.9345 | F13: =Assumptions!$B$22 -> 10 | G13: =E13/F13 -> 1.39345
A14: ElevenLabs Pro base | B14: =Assumptions!$B$17 -> 99 | D14: =Assumptions!$B$5 -> 1.55 | E14: =B14*D14 -> 153.45 | F14: =Assumptions!$B$22 -> 10 | G14: =E14/F14 -> 15.345
A15: Vercel / hosting | E15: =Assumptions!$B$18 -> 30 | F15: =Assumptions!$B$22 -> 10 | G15: =E15/F15 -> 3
A16: Fixed cost per client (AUD/mo) | G16: =SUM(G12:G15) -> 23.61345
A18: Margin summary — at full tier utilisation
A19: Tier | B19: Revenue | C19: Variable COGS | D19: Fixed alloc | E19: Total COGS | F19: Gross profit | G19: Gross margin %
A20: Starter | B20: =B5 -> 499 | C20: =G5 -> 126.456 | D20: =$G$16 -> 23.61345 | E20: =C20+D20 -> 150.06945 | F20: =B20-E20 -> 348.93055 | G20: =F20/B20 -> 0.69925962
A21: Growth | B21: =B6 -> 1499 | C21: =G6 -> 505.824 | D21: =$G$16 -> 23.61345 | E21: =C21+D21 -> 529.43745 | F21: =B21-E21 -> 969.56255 | G21: =F21/B21 -> 0.64680624
A22: Scale | B22: =B7 -> 3999 | C22: =G7 -> 1549.7 | D22: =$G$16 -> 23.61345 | E22: =C22+D22 -> 1573.3135 | F22: =B22-E22 -> 2425.6865 | G22: =F22/B22 -> 0.60657328
A23: Enterprise | B23: =B8 -> 7500 | C23: =G8 -> 3384.54 | D23: =$G$16 -> 23.61345 | E23: =C23+D23 -> 3408.1535 | F23: =B23-E23 -> 4091.8465 | G23: =F23/B23 -> 0.54557954

Sheet Scenarios
A1: Scenarios — what does a typical client cost vs pay?
A2: Forecasts margin across realistic usage profiles. Helps decide which tier to sell to a given client.
A4: Scenario | B4: Suggested tier | C4: Voice min | D4: Chat min | E4: Variable COGS | F4: Tier revenue | G4: Tier included | H4: Overage charged | I4: Gross margin %
A5: Light user (small office) | B5: Starter | C5: 100 | D5: 250 | E5: =C5*((Assumptions!$B$7*Assumptions!$B$5) + (Assumptions!$B$14*Assumptions!$B$9) + ((1-Assumptions!$B$14)*Assumptions!$B$10))+D5*((Assumptions!$B$8*Assumptions!$B$5)) -> 63.228 | F5: ='Tier Economics'!B5 -> 499 | G5: ='Tier Economics'!C5&" voice / "&'Tier Economics'!D5&" chat" -> 200 voice / 500 chat | H5: =MAX(0,C5-'Tier Economics'!C5)*'Tier Economics'!E5+MAX(0,D5-'Tier Economics'!D5)*'Tier Economics'!F5 -> 0 | I5: =(F5+H5-E5)/(F5+H5) -> 0.87329058
A6: Active SMB (storage, dental) | B6: Growth | C6: 600 | D6: 1500 | E6: =C6*((Assumptions!$B$7*Assumptions!$B$5) + (Assumptions!$B$14*Assumptions!$B$9) + ((1-Assumptions!$B$14)*Assumptions!$B$10))+D6*((Assumptions!$B$8*Assumptions!$B$5)) -> 379.368 | F6: ='Tier Economics'!B6 -> 1499 | G6: ='Tier Economics'!C6&" voice / "&'Tier Economics'!D6&" chat" -> 800 voice / 2000 chat | H6: =MAX(0,C6-'Tier Economics'!C6)*'Tier Economics'!E6+MAX(0,D6-'Tier Economics'!D6)*'Tier Economics'!F6 -> 0 | I6: =(F6+H6-E6)/(F6+H6) -> 0.74691928
A7: Mid-market multi-location | B7: Scale | C7: 1800 | D7: 4500 | E7: =C7*((Assumptions!$B$7*Assumptions!$B$5) + (Assumptions!$B$14*Assumptions!$B$9) + ((1-Assumptions!$B$14)*Assumptions!$B$10))+D7*((Assumptions!$B$8*Assumptions!$B$5)) -> 1138.104 | F7: ='Tier Economics'!B7 -> 3999 | G7: ='Tier Economics'!C7&" voice / "&'Tier Economics'!D7&" chat" -> 2500 voice / 6000 chat | H7: =MAX(0,C7-'Tier Economics'!C7)*'Tier Economics'!E7+MAX(0,D7-'Tier Economics'!D7)*'Tier Economics'!F7 -> 0 | I7: =(F7+H7-E7)/(F7+H7) -> 0.71540285
A8: Heavy enterprise | B8: Enterprise | C8: 5000 | D8: 12000 | E8: =C8*((Assumptions!$B$7*Assumptions!$B$5) + (Assumptions!$B$14*Assumptions!$B$9) + ((1-Assumptions!$B$14)*Assumptions!$B$10))+D8*((Assumptions!$B$8*Assumptions!$B$5)) -> 3099.4 | F8: ='Tier Economics'!B8 -> 7500 | G8: ='Tier Economics'!C8&" voice / "&'Tier Economics'!D8&" chat" -> 5500 voice / 13000 chat | H8: =MAX(0,C8-'Tier Economics'!C8)*'Tier Economics'!E8+MAX(0,D8-'Tier Economics'!D8)*'Tier Economics'!F8 -> 0 | I8: =(F8+H8-E8)/(F8+H8) -> 0.58674667
A11: Custom client estimator — enter your own usage
A12: Scenario | B12: Suggested tier | C12: Voice min | D12: Chat min | E12: Variable COGS | F12: Tier revenue | G12: Tier included | H12: Overage charged | I12: Gross margin %
A13: My client #1 | B13: Starter | C13: 300 | D13: 700 | E13: =C13*((Assumptions!$B$7*Assumptions!$B$5) + (Assumptions!$B$14*Assumptions!$B$9) + ((1-Assumptions!$B$14)*Assumptions!$B$10))+D13*((Assumptions!$B$8*Assumptions!$B$5)) -> 183.484 | F13: =VLOOKUP(B13,'Tier Economics'!$A$5:$F$8,2,FALSE) -> 499 | G13: =VLOOKUP(B13,'Tier Economics'!$A$5:$F$8,3,FALSE)&" voice / "&VLOOKUP(B13,'Tier Economics'!$A$5:$F$8,4,FALSE)&" chat" -> 200 voice / 500 chat | H13: =MAX(0,C13-VLOOKUP(B13,'Tier Economics'!$A$5:$F$8,3,FALSE))*VLOOKUP(B13,'Tier Economics'!$A$5:$F$8,5,FALSE)+MAX(0,D13-VLOOKUP(B13,'Tier Economics'!$A$5:$F$8,4,FALSE))*VLOOKUP(B13,'Tier Economics'!$A$5:$F$8,6,FALSE) -> 230 | I13: =(F13+H13-E13)/(F13+H13) -> 0.74830727
A14: My client #2 | B14: Starter | C14: 300 | D14: 700 | E14: =C14*((Assumptions!$B$7*Assumptions!$B$5) + (Assumptions!$B$14*Assumptions!$B$9) + ((1-Assumptions!$B$14)*Assumptions!$B$10))+D14*((Assumptions!$B$8*Assumptions!$B$5)) -> 183.484 | F14: =VLOOKUP(B14,'Tier Economics'!$A$5:$F$8,2,FALSE) -> 499 | G14: =VLOOKUP(B14,'Tier Economics'!$A$5:$F$8,3,FALSE)&" voice / "&VLOOKUP(B14,'Tier Economics'!$A$5:$F$8,4,FALSE)&" chat" -> 200 voice / 500 chat | H14: =MAX(0,C14-VLOOKUP(B14,'Tier Economics'!$A$5:$F$8,3,FALSE))*VLOOKUP(B14,'Tier Economics'!$A$5:$F$8,5,FALSE)+MAX(0,D14-VLOOKUP(B14,'Tier Economics'!$A$5:$F$8,4,FALSE))*VLOOKUP(B14,'Tier Economics'!$A$5:$F$8,6,FALSE) -> 230 | I14: =(F14+H14-E14)/(F14+H14) -> 0.74830727
A15: My client #3 | B15: Starter | C15: 300 | D15: 700 | E15: =C15*((Assumptions!$B$7*Assumptions!$B$5) + (Assumptions!$B$14*Assumptions!$B$9) + ((1-Assumptions!$B$14)*Assumptions!$B$10))+D15*((Assumptions!$B$8*Assumptions!$B$5)) -> 183.484 | F15: =VLOOKUP(B15,'Tier Economics'!$A$5:$F$8,2,FALSE) -> 499 | G15: =VLOOKUP(B15,'Tier Economics'!$A$5:$F$8,3,FALSE)&" voice / "&VLOOKUP(B15,'Tier Economics'!$A$5:$F$8,4,FALSE)&" chat" -> 200 voice / 500 chat | H15: =MAX(0,C15-VLOOKUP(B15,'Tier Economics'!$A$5:$F$8,3,FALSE))*VLOOKUP(B15,'Tier Economics'!$A$5:$F$8,5,FALSE)+MAX(0,D15-VLOOKUP(B15,'Tier Economics'!$A$5:$F$8,4,FALSE))*VLOOKUP(B15,'Tier Economics'!$A$5:$F$8,6,FALSE) -> 230 | I15: =(F15+H15-E15)/(F15+H15) -> 0.74830727

Sheet Setup Fees
A1: Setup Fees — one-time, per client
A2: Recovers onboarding labour. Approximate engineering rate: AUD $1,500–$2,500/day.
A4: Package | B4: Fee (AUD) | C4: What's included | D4: Effort estimate
A5: Lite Setup | B5: 1500 | C5: Standard KB upload (up to 20 docs), 1 Twilio AU local number, default web widget, 2 standard n8n workflows (booking + inquiry), 2hr training, 1 week post-launch support | D5: ~3 days dev work
A6: Standard Setup | B6: 3500 | C6: Custom KB tuning, 1-2 Twilio numbers (local + mobile), branded web widget, up to 5 custom n8n workflows, CRM hand-off, 5hr training, 2 weeks support | D6: ~5-7 days dev work
A7: Enterprise Setup | B7: 8000 | C7: Custom ElevenLabs voice clone, multi-agent flows, full CRM integration, dedicated workflow build, SLA, 4 weeks support — from $8K, scope-priced | D7: 10+ days dev work, sales-led

Sheet Fixed Costs
A1: Fixed Platform Costs (monthly, before any client revenue)
A2: These costs exist regardless of client count. Divide across all clients to estimate fixed-cost drag per client.
A4: Service | B4: Plan | C4: Native price | D4: Monthly AUD (est.) | E4: Notes
A5: Supabase | B5: Pro | C5: USD $25 | D5: 39 | E5: 8GB DB, 100K MAU, 100GB storage, 250GB egress. Overage: $0.125/GB DB, $0.09/GB egress.
A6: n8n | B6: Hostinger KVM 2 (self-host) | C6: USD $8.99 | D6: 14 | E6: Recommended. Unlimited executions. 2 vCPU, 8GB RAM. ~1 day devops setup.
A7: n8n (alt) | B7: Cloud Pro (current) | C7: EUR €50 | D7: 83 | E7: 10K executions/month — will cap fast as clients add workflows.
A8: ElevenLabs | B8: Pro base plan | C8: USD $99 | D8: 153 | E8: Required to access Agents add-on. 500K credits/month included.
A9: Vercel / hosting | B9: Hobby/Pro | C9: AUD $30 | D9: 30 | E9: Web dashboard hosting. Already in use.
A10: Retell KBs (after 10) | B10: Per KB/mo | C10: USD $8 | D10: 12 | E10: Negligible until you exceed 10 clients.
A11: OpenAI direct | B11: API usage | C11: Variable | D11: 30 | E11: Embeddings + occasional direct API for n8n nodes. Conservative estimate.
A12: TOTAL (recommended stack: self-host n8n) | D12: =D5+D6+D8+D9+D10+D11 -> 278
A13: TOTAL (if staying on n8n Cloud Pro) | D13: =D5+D7+D8+D9+D10+D11 -> 347

Sheet Year-1 Projection
A1: Year-1 Projection — Anchor Client Ramp (5 → 10 clients)
A2: Conservative ramp: 1 client month 1, +1 per month, plateau at 8. Mix: 50% Starter, 35% Growth, 15% Scale. 70% utilisation assumption. Anchors get 50% off month 1 (case-study trade).
A4: Metric | B4: M1 | C4: M2 | D4: M3 | E4: M4 | F4: M5 | G4: M6 | H4: M7 | I4: M8 | J4: M9 | K4: M10 | L4: M11 | M4: M12 | N4: Year 1 Total
A5: Active clients | B5: 1 | C5: 2 | D5: 3 | E5: 4 | F5: 5 | G5: 6 | H5: 7 | I5: 8 | J5: 8 | K5: 8 | L5: 9 | M5: 10 | N5: =AVERAGE(B5:M5) -> 5.9166667
A6: MRR (avg AUD per client × clients) | B6: 687 | C6: 2061 | D6: 3435 | E6: 4809 | F6: 6183 | G6: 7557 | H6: 8931 | I6: 10305 | J6: 10992 | K6: 10992 | L6: 11679 | M6: 13053 | N6: =SUM(B6:M6) -> 90684
A7: Setup fees (new clients × mix avg) | B7: 3175 | C7: 3175 | D7: 3175 | E7: 3175 | F7: 3175 | G7: 3175 | H7: 3175 | I7: 3175 | J7: 0 | K7: 0 | L7: 3175 | M7: 3175 | N7: =SUM(B7:M7) -> 31750
A8: Total revenue | B8: =B6+B7 -> 3862 | C8: =C6+C7 -> 5236 | D8: =D6+D7 -> 6610 | E8: =E6+E7 -> 7984 | F8: =F6+F7 -> 9358 | G8: =G6+G7 -> 10732 | H8: =H6+H7 -> 12106 | I8: =I6+I7 -> 13480 | ... M8: =M6+M7 -> 16228 | N8: =SUM(B8:M8) -> 122434
A9: Variable COGS (70% util) | B9: 370.02 | C9: 740.04 | D9: 1110.06 | E9: 1480.08 | F9: 1850.1 | G9: 2220.12 | H9: 2590.14 | I9: 2960.16 | J9: 2960.16 | K9: 2960.16 | L9: 3330.18 | M9: 3700.2 | N9: =SUM(B9:M9) -> 26271.42
A10: Fixed platform costs | B10: 266 | C10: 266 | D10: 266 | E10: 266 | F10: 266 | G10: 266 | H10: 266 | I10: 266 | J10: 266 | K10: 266 | L10: 266 | M10: 266 | N10: =SUM(B10:M10) -> 3192
A11: Gross profit | B11: =B8-B9-B10 -> 3225.98 | C11: =C8-C9-C10 -> 4229.96 | D11: =D8-D9-D10 -> 5233.94 | E11: =E8-E9-E10 -> 6237.92 | F11: =F8-F9-F10 -> 7241.9 | G11: =G8-G9-G10 -> 8245.88 | H11: =H8-H9-H10 -> 9249.86 | I11: =I8-I9-I10 -> 10253.84 | ... M11: =M8-M9-M10 -> 12261.8 | N11: =SUM(B11:M11) -> 92970.58
A12: Gross margin % | B12: =IFERROR(B11/B8,0) -> 0.83531331 | C12: =IFERROR(C11/C8,0) -> 0.80786096 | D12: =IFERROR(D11/D8,0) -> 0.79182148 | E12: =IFERROR(E11/E8,0) -> 0.78130261 | F12: =IFERROR(F11/F8,0) -> 0.77387262 | G12: =IFERROR(G11/G8,0) -> 0.76834514 | H12: =IFERROR(H11/H8,0) -> 0.76407236 | I12: =IFERROR(I11/I8,0) -> 0.76067062 | ... M12: =IFERROR(M11/M8,0) -> 0.75559527 | N12: =N11/N8 -> 0.75935263
A14: Notes & sensitivities
A15: • Conservative: assumes 0 overage revenue (real clients will likely exceed included usage on Scale tier).
A16: • Weighted MRR per client = AUD $1,374 (50% Starter / 35% Growth / 15% Scale).
A17: • Weighted setup fee per client = AUD $3,175 (same mix).
A18: • Anchor deal: 50% off month 1 only for case-study trade. Subsequent months at full price.
A19: • If you switch to free trial instead, deduct ~AUD $300-$500 in variable COGS exposure per trial month.
A20: • Fixed costs assume self-host n8n on Hostinger; add ~AUD $70/mo if staying on n8n Cloud Pro.
A21: • Headcount cost NOT included (founder + dev + support). This is gross profit before salaries.

Sheet Risk Register
A1: Risk Register — cost & operational risks
A2: Six known PAYG / scaling risks the founder should weigh before launch.
A4: Risk | B4: Description | C4: Severity | D4: Mitigation
A5: Concurrency cliff | B5: Retell includes 20 concurrent calls. Above that = USD $8 per concurrent slot per month. | C5: High | D5: Alert at 15 concurrent. Charge Enterprise tier a surcharge if >20 needed.
A6: ElevenLabs base plan floor cost | B6: USD $99/mo Pro plan is required to unlock Agents add-on. Spread thin across <5 clients. | C6: Medium | D6: Build into Starter pricing OR absorb as marketing cost during ramp.
A7: n8n execution limits (Cloud Pro) | B7: 10K executions/mo cap. Each call/chat triggers multiple workflows. One Growth client can use 1K+ execs. | C7: High | D7: MIGRATE to self-host on Hostinger before client #3. Unlimited executions for $14/mo AUD.
A8: Peak-hour PAYG explosion | B8: Marketing campaign tripling volume in 48hrs = uncapped voice/chat cost burn. | C8: High | D8: App-layer soft-cap: Supabase counter + Retell webhook. Alert client at 90% of included minutes.
A9: Custom ElevenLabs voice upgrade | B9: Per-client branded voice clone = Pro/Enterprise ElevenLabs feature. | C9: Low | D9: Charge AUD $500–$1,500 one-time per cloned voice as Enterprise add-on.
A10: Outbound mobile call cost (3× local) | B10: Twilio AU outbound mobile = $0.075/min vs local $0.0252. Outbound campaigns burn margin fast. | C10: Medium | D10: Separate 'Outbound Campaign' SKU. Higher per-min overage rate for outbound-heavy clients.
